mitmweb_client/__init__.py
mitmweb_client/mitmweb_client.py
mitmweb_client-0.0.1.dist-info/LICENSE
mitmweb_client-0.0.1.dist-info/WHEEL
mitmweb_client-0.0.1.dist-info/METADATA
mitmweb_client-0.0.1.dist-info/RECORD
